llg/__init__.py
llg/_tools.py
llg/bucket.py
llg/cli.py
llg/geometry.py
llg/plot_states.py
llg/predefined_structures.py
llg/sample.py
llg/simulation.py
llg/site.py
llg/store.py
llg/system.py
llg/functions/__init__.py
llg/functions/energy.py
llg/functions/external_fields.py
llg/functions/heun.py
llg/functions/magnetization.py
llg/functions/spin_fields.py
llg-1.1.0.dist-info/AUTHORS.rst
llg-1.1.0.dist-info/LICENSE
llg-1.1.0.dist-info/METADATA
llg-1.1.0.dist-info/WHEEL
llg-1.1.0.dist-info/entry_points.txt
llg-1.1.0.dist-info/top_level.txt
llg-1.1.0.dist-info/RECORD
