Metadata-Version: 2.1
Name: llg
Version: 1.1.0
Summary: Python package to solve the LLG equation by using the Heun scheme.
Home-page: https://github.com/lufvelasquezgo/llg
Author: Luisa Fernanda Velásquez González
Author-email: lufvelasquezgo@unal.edu.co
License: MIT license
Keywords: llg
Platform: UNKNOWN
Classifier: License :: OSI Approved :: MIT License
Classifier: Natural Language :: English
Classifier: Programming Language :: Python :: 3.7
Classifier: Programming Language :: Python :: 3.8
Classifier: Programming Language :: Python :: 3.9
Requires-Dist: Click (>=6.0)
Requires-Dist: numpy (>=1.17.0)
Requires-Dist: tqdm (>=4.32.2)
Requires-Dist: h5py (>=2.10.0)
Requires-Dist: matplotlib (>=3.1.2)
Requires-Dist: Pillow (>=7.0.0)
Requires-Dist: moviepy (>=1.0.1)
Requires-Dist: vapory (>=0.1.1)
Requires-Dist: nptyping (>=1.0.1)
Requires-Dist: numba (>=0.48.0)
